bpputilmodule/__init__.py
bpputilmodule/bppQboUtil.py
bpputilmodule/bppUtil.py
bpputilmodule-0.0.1.dist-info/LICENSE.txt
bpputilmodule-0.0.1.dist-info/METADATA
bpputilmodule-0.0.1.dist-info/WHEEL
bpputilmodule-0.0.1.dist-info/top_level.txt
bpputilmodule-0.0.1.dist-info/RECORD
