Metadata-Version: 2.1
Name: bpputilmodule
Version: 0.0.1
Summary: BPP accounting API internal library to reduce redundant code
Home-page: https://gitlab.com/jkondepati/bpputils
Author: Jeevani
Author-email: jkondepati@bluepenguin.com
Project-URL: repository, https://gitlab.com/jkondepati/bpputils
Classifier: Programming Language :: Python :: 3
Classifier: License :: OSI Approved :: MIT License
Classifier: Operating System :: OS Independent
Requires-Python: >=3.6
License-File: LICENSE.txt
Requires-Dist: requests
Requires-Dist: json
